INSTALL
LICENSE
MANIFEST.in
README
README.rst
setup.cfg
setup.py
drainers/__init__.py
drainers/base.py
drainers/buffered.py
drainers.egg-info/PKG-INFO
drainers.egg-info/SOURCES.txt
drainers.egg-info/dependency_links.txt
drainers.egg-info/not-zip-safe
drainers.egg-info/top_level.txt
examples/buffer_results.py
examples/simple_annotate_date.py
examples/simple_find.py
examples/simple_kill_sleep.py
examples/simple_ls.py