Metadata-Version: 1.0
Name: drainers
Version: 0.0.3
Summary: Event-based draining of process output
Home-page: http://github.com/nvie/python-drainers/
Author: Vincent Driessen
Author-email: vincent@datafox.nl
License: BSD
Platform: any
Classifier: Development Status :: 2 - Pre-Alpha
Classifier: Operating System :: OS Independent
Classifier: Programming Language :: Python
Classifier: Programming Language :: Python :: 2.6
Classifier: Intended Audience :: Developers
Classifier: License :: OSI Approved :: BSD License
Classifier: Operating System :: POSIX
Classifier: Topic :: Software Development :: Libraries :: Python Modules
